rocket/__init__.py
rocket/rocket.py
rocket-moamed/__init__.py
rocket-moamed/rocket.py
rocket_moamed-0.1.0.dist-info/LICENSE.txt
rocket_moamed-0.1.0.dist-info/METADATA
rocket_moamed-0.1.0.dist-info/WHEEL
rocket_moamed-0.1.0.dist-info/top_level.txt
rocket_moamed-0.1.0.dist-info/RECORD
