Metadata-Version: 2.1
Name: rocket-moamed
Version: 0.1.0
Summary: A package for simulating rockets and shuttles.
Author: Boufafa MOhamed
Author-email: boufafa.moamed@gmail.com
Classifier: Programming Language :: Python :: 3
Classifier: License :: OSI Approved :: MIT License
Classifier: Operating System :: OS Independent
Requires-Python: >=3.6
License-File: LICENSE.txt
